{
  "workspaces": {
    "左右分布：源码+阅读": {
      "main": {
        "id": "a23640c49edd0f8a",
        "type": "split",
        "children": [
          {
            "id": "2ed17375ce82ce82",
            "type": "tabs",
            "children": [
              {
                "id": "64300f4d6dda7287",
                "type": "leaf",
                "state": {
                  "type": "markdown",
                  "state": {
                    "file": "Languages/Python/NumPy.md",
                    "mode": "source",
                    "source": true
                  }
                }
              }
            ]
          },
          {
            "id": "91e43315142dda95",
            "type": "tabs",
            "children": [
              {
                "id": "8a37e041a741765b",
                "type": "leaf",
                "state": {
                  "type": "markdown",
                  "state": {
                    "file": "Languages/Python/NumPy.md",
                    "mode": "preview",
                    "source": false
                  }
                }
              }
            ]
          }
        ],
        "direction": "vertical"
      },
      "left": {
        "id": "3155338261bf236f",
        "type": "split",
        "children": [
          {
            "id": "bcb11dc63b8c4711",
            "type": "tabs",
            "children": [
              {
                "id": "12f36a133287a76c",
                "type": "leaf",
                "state": {
                  "type": "file-explorer",
                  "state": {
                    "sortOrder": "alphabetical"
                  }
                }
              },
              {
                "id": "54ddf341fcb54ac6",
                "type": "leaf",
                "state": {
                  "type": "search",
                  "state": {
                    "query": "",
                    "matchingCase": false,
                    "explainSearch": false,
                    "collapseAll": false,
                    "extraContext": false,
                    "sortOrder": "alphabetical"
                  }
                }
              },
              {
                "id": "3c271a634b136d32",
                "type": "leaf",
                "state": {
                  "type": "starred",
                  "state": {}
                }
              }
            ]
          }
        ],
        "direction": "horizontal",
        "width": 200
      },
      "right": {
        "id": "250e0b34d490eddc",
        "type": "split",
        "children": [
          {
            "id": "7e048932bfa41a91",
            "type": "tabs",
            "children": [
              {
                "id": "2141321c757351e9",
                "type": "leaf",
                "state": {
                  "type": "outline",
                  "state": {
                    "file": "Languages/Python/NumPy.md"
                  }
                }
              },
              {
                "id": "18fe1fdb067e546e",
                "type": "leaf",
                "state": {
                  "type": "backlink",
                  "state": {
                    "file": "Languages/Python/NumPy.md",
                    "collapseAll": false,
                    "extraContext": false,
                    "sortOrder": "alphabetical",
                    "showSearch": false,
                    "searchQuery": "",
                    "backlinkCollapsed": false,
                    "unlinkedCollapsed": true
                  }
                }
              },
              {
                "id": "175befeef79ffc50",
                "type": "leaf",
                "state": {
                  "type": "outgoing-link",
                  "state": {
                    "file": "Languages/Python/NumPy.md",
                    "linksCollapsed": false,
                    "unlinkedCollapsed": true
                  }
                }
              },
              {
                "id": "ea925a13062a1d61",
                "type": "leaf",
                "state": {
                  "type": "tag",
                  "state": {
                    "sortOrder": "frequency",
                    "useHierarchy": false
                  }
                }
              }
            ]
          }
        ],
        "direction": "horizontal",
        "width": 200
      },
      "left-ribbon": {
        "hiddenItems": {
          "switcher:打开快速切换": false,
          "graph:查看关系图谱": false,
          "canvas:新建白板": false,
          "daily-notes:打开/创建今天的日记": false,
          "templates:插入模板": false,
          "command-palette:打开命令面板": false,
          "workspaces:管理工作区布局": false
        }
      },
      "active": "64300f4d6dda7287"
    }
  },
  "active": "左右分布：源码+阅读"
}